{
    "answers": [],
    "post_id": "6088150",
    "question": "I am a 39 old hispanic american and i have no proplems with an eraction but i do have problem on finding the hole it only\u00a0\u00a0take me two strokes and i am done not even that maybe 1 stroke and i am done i also have diabetes at the age of 36 old i also have bi polar at the age of 36 old and i am taking seroquel what can i do on my own before talking to my personal Doctor on this issue also my penis isn't long i weigh about 275 lbs over weight not one muscles on me truly your Mark V Big Spring Tx",
    "timestamp": "1283232054",
    "title": "Problems with ejacuation"
}