{
    "answers": [
        {
            "answer": "Did he use protection?",
            "post_id": "3328004",
            "timestamp": "1219777895",
            "votes": 0
        },
        {
            "answer": "He did not use protection if was e giving to him not him to me bacially he forced me to put it in him. they say tops are low risk but want to verify it cause rape is serious and they tested me for every thing and every thign else is negative waiting on hiv test to come back now. Just want to know if i could if got any thing if i was the top and he was the bottom in that sense of that rape.",
            "post_id": "3328042",
            "timestamp": "1219778355",
            "votes": 0
        },
        {
            "answer": "You will need to test at 6 weeks then 3 months for a conclusive result sorry thats just how it is.Goodluck my friend",
            "post_id": "3328078",
            "timestamp": "1219778977",
            "votes": 0
        },
        {
            "answer": "with what happened was it a low risk ?and most likely i did not contract anything?",
            "post_id": "3328091",
            "timestamp": "1219779120",
            "votes": 0
        },
        {
            "answer": "Unprotected anal is not low risk top or bottomHow well do you know the person who raped you ?You had a risk maybe topping is lower but still you had a risk",
            "post_id": "3328118",
            "timestamp": "1219779518",
            "votes": 0
        },
        {
            "answer": "I did not know the person that well .I just know some dictor's told me low risk cause i was nto recieving but i do not know.I also got thrush but the doctor last night said if i was infected would not show up this soon. is that true and besides i am a diabetic. so that might be what it is from.",
            "post_id": "3328138",
            "timestamp": "1219779776",
            "votes": 0
        },
        {
            "answer": "It takes anywhere from 22 days to 3 monthsmost will have a positive result by 6 weeks if they are going to be positiveI am sorry you got raped but dont stress over it it will only make things worse for you",
            "post_id": "3328184",
            "timestamp": "1219780302",
            "votes": 0
        },
        {
            "answer": "Thanks for your help",
            "post_id": "3328328",
            "timestamp": "1219782173",
            "votes": 0
        }
    ],
    "post_id": "3327945",
    "question": "I got a question I was raped by a male back in the end of juneHe forced\u00a0\u00a0me to have anal sex with him. I want to know if he made me do this was i at risk for getting hiv i got tested but the test has not come back yet. The only thing i know is i got thrush but i also have diabetes.could i have gotten it from that or was it such a low risk and nothing to worry about?ThanksKY BOY",
    "timestamp": "1219777343",
    "title": "Question about hiv"
}