{
    "answers": [
        {
            "answer": "Awesome news mama.",
            "post_id": "10194019",
            "timestamp": "1396675943",
            "user_id": "user_7106406",
            "user_link": "/personal_pages/user/7106406",
            "votes": "0"
        },
        {
            "answer": "Thank you!!!!",
            "post_id": "10194028",
            "timestamp": "1396676156",
            "user_id": "user_6429572",
            "user_link": "/personal_pages/user/6429572",
            "votes": "0"
        },
        {
            "answer": "Congratulations!",
            "post_id": "10194107",
            "timestamp": "1396677748",
            "user_id": "user_6822962",
            "user_link": "/personal_pages/user/6822962",
            "votes": "0"
        },
        {
            "answer": "Thank you!!!!",
            "post_id": "10194417",
            "timestamp": "1396688522",
            "user_id": "user_6429572",
            "user_link": "/personal_pages/user/6429572",
            "votes": "0"
        },
        {
            "answer": "why didn't I see this post? I'm so consumed in messaging you I don't check your page anymore! lolanywho, again, yayyyyyy!!!! God is good! \u2764",
            "post_id": "10194418",
            "timestamp": "1396688771",
            "user_id": "user_7721203",
            "user_link": "/personal_pages/user/7721203",
            "votes": "0"
        },
        {
            "answer": "O yaaay! That's great news. Happy for you!",
            "post_id": "10194421",
            "timestamp": "1396688864",
            "user_id": "user_7001988",
            "user_link": "/personal_pages/user/7001988",
            "votes": "0"
        },
        {
            "answer": "Lol I hear that OctoberMommy lol. And thank you YoungLadyDay, I am so happy. Now just to keep it in check.",
            "post_id": "10194426",
            "timestamp": "1396689099",
            "user_id": "user_6429572",
            "user_link": "/personal_pages/user/6429572",
            "votes": "0"
        }
    ],
    "post_id": "10194011",
    "question": "So I got my test results back today and everything was good. No preeclampsia!!!! I still have to be on bed rest to make sure with my BP still going wonky. But I am soooo happy with the great news!!!!",
    "timestamp": "1396675822",
    "title": "Good News",
    "user_id": "user_6429572",
    "user_link": "/personal_pages/user/6429572"
}