{
    "answers": [
        {
            "answer": "It's pretty common to get nosebleeds in pregnancy.\u00a0\u00a0This doesn't rule out preeclampsia, but it probably doesn't indicate it either.",
            "post_id": "5722492",
            "timestamp": "1274849043",
            "user_id": "user_134578",
            "user_link": "/personal_pages/user/134578",
            "votes": "0"
        },
        {
            "answer": "I agree with Annie - I blow my nose too and there is blood - I think it has to do with the increased blood flow while pregnant and the vessels there are more delicate.\u00a0\u00a0But mention to your dr at your next appt.",
            "post_id": "5722983",
            "timestamp": "1274870951",
            "user_id": "user_1102290",
            "user_link": "/personal_pages/user/1102290",
            "votes": "0"
        },
        {
            "answer": "I've had this happen almost since I found out I was pregnant this time....I agree, mention it to doc, but you can ask my husband all of my snot rags (sorry LOL) have been bloody for the past 8 months :). Like you, nothing MAJOR, but enough blood to say \"hey look, blood!\"",
            "post_id": "5723143",
            "timestamp": "1274875805",
            "user_id": "user_1035252",
            "user_link": "/personal_pages/user/1035252",
            "votes": "0"
        },
        {
            "answer": "I've also had this happen since first finding out I was pregnant.\u00a0\u00a0It's actually impossible for me to blow my nose without seeing blood.\u00a0\u00a0But I would definitely get your blood pressure checked anyway.",
            "post_id": "5723752",
            "timestamp": "1274887327",
            "user_id": "user_423860",
            "user_link": "/personal_pages/user/423860",
            "votes": "0"
        },
        {
            "answer": "Thanks everyone, it is nice to know it is so common.I rang my OB and they said that it sounds normal and if I'm still worried to get my normal doc to check my blood pressure to ease my mind. (much cheaper that way)I think I'll just wait for my next check-up which is on the 4th June and not too far away now.",
            "post_id": "5726687",
            "timestamp": "1274947304",
            "user_id": "user_448723",
            "user_link": "/personal_pages/user/448723",
            "votes": "0"
        },
        {
            "answer": "I have had blood in my tissue and even bad bloody noses all thru the pregnancy and was told not to worry about it, its normal.",
            "post_id": "5735217",
            "timestamp": "1275159510",
            "user_id": "user_1066426",
            "user_link": "/personal_pages/user/1066426",
            "votes": "0"
        }
    ],
    "post_id": "5722126",
    "question": "Over the last week I have had a cold and so have been blowing my nose. I have noticed that there is often blood in the tissue with the snot. It isn't very much, but it is there. What worries me is that I get pre ecclampsia and I think that might be a symptom of elevated blood pressure.I guess I need to check this one out with my doctor, but I was just wondering if this is happening to anyone else?",
    "timestamp": "1274838928",
    "title": "Blood in my snot?",
    "user_id": "user_448723",
    "user_link": "/personal_pages/user/448723"
}