{
    "answers": [
        {
            "answer": "My feels swollen after sex, I'm 29 weeks",
            "post_id": "12632727",
            "timestamp": "1431749632",
            "user_id": "user_11788715",
            "user_link": "/personal_pages/user/11788715",
            "votes": 0
        },
        {
            "answer": "I haven't had sex in a week... This feels sooo weird!!!",
            "post_id": "12632742",
            "timestamp": "1431749904",
            "user_id": "user_11149705",
            "user_link": "/personal_pages/user/11149705",
            "votes": 0
        },
        {
            "answer": "I saw my Dr today because my vulva was swollen and felt irritated I haven't had sex in over a month but I was worried because ei can't see myself anymore... Dr said that I need to move around more, stand more walk more I sit all day at work and she said I can be puffing in the area from blood and fluid pooling there similar to feet",
            "post_id": "12632951",
            "timestamp": "1431752984",
            "user_id": "user_11531533",
            "user_link": "/personal_pages/user/11531533",
            "votes": 0
        },
        {
            "answer": "O ok. How many weeks r u? I just want it to feel normal again",
            "post_id": "12634637",
            "timestamp": "1431789671",
            "user_id": "user_11149705",
            "user_link": "/personal_pages/user/11149705",
            "votes": 0
        },
        {
            "answer": "I'm 32 1/2 wks and I feel swollen alot to sometimes hard to walk cuz it feels weird or slightly sore",
            "post_id": "12646421",
            "timestamp": "1431959748",
            "user_id": "user_11370759",
            "user_link": "/personal_pages/user/11370759",
            "votes": 0
        },
        {
            "answer": "Omg that's how I feel even though today has been better!",
            "post_id": "12657377",
            "timestamp": "1432086887",
            "user_id": "user_11149705",
            "user_link": "/personal_pages/user/11149705",
            "votes": 0
        },
        {
            "answer": "Is it worse when u squat down? Cuz ive been having tht problem kinda. It feels painful when i squat down and ive been wondering why it has been hurtin like this but i try to walk all the time",
            "post_id": "12658439",
            "timestamp": "1432097007",
            "user_id": "user_11403460",
            "user_link": "/personal_pages/user/11403460",
            "votes": 0
        },
        {
            "answer": "Yes. I feel like I can't even squat or bend over. I go see my doctor tomorrow so hopefully I find out what it is since I'm seeing him every week for preeclampsia.",
            "post_id": "12658650",
            "timestamp": "1432099774",
            "user_id": "user_11149705",
            "user_link": "/personal_pages/user/11149705",
            "votes": 0
        }
    ],
    "post_id": "12632618",
    "question": "Sorry if this is too much info but I'm 32 weeks and I don't remember my last pregnancy 10 years ago. I feel open and my vagina feels swollen! Is this normal?",
    "timestamp": "1431748096",
    "title": "tmi...my vagina feels open/swollen.",
    "user_id": "user_11149705",
    "user_link": "/personal_pages/user/11149705"
}